adsdatahub/__init__.py
adsdatahub/_helpers.py
adsdatahub/exceptions.py
adsdatahub/py.typed
adsdatahub/types.py
adsdatahub/client/__init__.py
adsdatahub/client/client.py
adsdatahub/client/mock_client.py
adsdatahub/client/query_result.py
adsdatahub/client/real_client.py
adsdatahub/client/customer/__init__.py
adsdatahub/client/customer/customer.py
adsdatahub/client/customer/mock_customer.py
adsdatahub/client/customer/real_customer.py
adsdatahub/client/parameters/__init__.py
adsdatahub/client/parameters/primitive_parameters.py
adsdatahub/client/parameters/pydantic_parameters.py
adsdatahub/client/query_job/__init__.py
adsdatahub/client/query_job/mock_query_job.py
adsdatahub/client/query_job/query_job.py
adsdatahub/client/query_job/real_query_job.py
adsdatahub/restapi/__init__.py
adsdatahub/restapi/client.py
adsdatahub/restapi/mock_client.py
adsdatahub/restapi/real_client.py
adsdatahub/restapi/http/__init__.py
adsdatahub/restapi/http/client.py
adsdatahub/restapi/http/mock_client.py
adsdatahub/restapi/http/real_client.py
adsdatahub/restapi/resources/__init__.py
adsdatahub/restapi/resources/analysis_queries/__init__.py
adsdatahub/restapi/resources/analysis_queries/list.py
adsdatahub/restapi/resources/analysis_queries/start_transient.py
adsdatahub/restapi/resources/analysis_queries/validate.py
adsdatahub/restapi/resources/analysis_query/__init__.py
adsdatahub/restapi/resources/analysis_query/start.py
adsdatahub/restapi/resources/operation/__init__.py
adsdatahub/restapi/resources/operation/wait.py
adsdatahub/restapi/resources/operations/__init__.py
adsdatahub/restapi/resources/operations/list.py
adsdatahub/restapi/schemas/__init__.py
adsdatahub/restapi/schemas/_model.py
adsdatahub/restapi/schemas/analysis_queries_start.py
adsdatahub/restapi/schemas/analysis_query.py
adsdatahub/restapi/schemas/analysis_query_metadata.py
adsdatahub/restapi/schemas/column.py
adsdatahub/restapi/schemas/column_info.py
adsdatahub/restapi/schemas/column_summary_rule.py
adsdatahub-0.0.7.dist-info/METADATA
adsdatahub-0.0.7.dist-info/WHEEL
adsdatahub-0.0.7.dist-info/RECORD
