Metadata-Version: 2.4
Name: adsdatahub
Version: 0.0.7
Summary: Ads Data Hub API client for Python
Author-email: ya7010 <ya7010@outlook.com>
Requires-Python: >=3.11
Requires-Dist: google-api-python-client
Requires-Dist: google-cloud-bigquery
Requires-Dist: httpx
Requires-Dist: pydantic
Requires-Dist: typing-extensions
